woodenwaiter/__init__.py
woodenwaiter/woodenwaiter.py
woodenwaiter-0.0.4.dist-info/DESCRIPTION.rst
woodenwaiter-0.0.4.dist-info/METADATA
woodenwaiter-0.0.4.dist-info/RECORD
woodenwaiter-0.0.4.dist-info/WHEEL
woodenwaiter-0.0.4.dist-info/metadata.json
woodenwaiter-0.0.4.dist-info/top_level.txt
