Metadata-Version: 2.0
Name: woodenwaiter
Version: 0.0.4
Summary: A producer-customer model based on redis
Home-page: https://github.com/haoranzeus/woodenwaiter
Author: zhanghaoran
Author-email: haoranzeus@gmail.com
License: UNKNOWN
Platform: UNKNOWN
Requires-Dist: redis
